pytest_energy_reporter/__init__.py
pytest_energy_reporter/analyze.py
pytest_energy_reporter/measurement.py
pytest_energy_reporter/plugin.py
pytest_energy_reporter/util.py
pytest_energy_reporter-0.5.2.dist-info/entry_points.txt
pytest_energy_reporter-0.5.2.dist-info/license.txt
pytest_energy_reporter-0.5.2.dist-info/METADATA
pytest_energy_reporter-0.5.2.dist-info/WHEEL
pytest_energy_reporter-0.5.2.dist-info/RECORD
