Metadata-Version: 2.1
Name: pytest_energy_reporter
Version: 0.5.2
Summary: An energy estimation reporter for pytest
License: license.txt
Keywords: pytest,energy,reporter
Author: Delano Flipse
Author-email: delanoflipse@gmail.com
Maintainer: Delano Flipse
Maintainer-email: delanoflipse@gmail.com
Requires-Python: >=3.10,<4.0
Classifier: Development Status :: 3 - Alpha
Classifier: Framework :: Pytest
Classifier: Intended Audience :: Developers
Classifier: License :: Other/Proprietary License
Classifier: Programming Language :: Python
Classifier: Programming Language :: Python :: 3
Classifier: Programming Language :: Python :: 3.10
Classifier: Programming Language :: Python :: 3.11
Classifier: Programming Language :: Python :: 3.12
Requires-Dist: energy-consumption-reporter (>=0.1.3,<0.2.0)
Requires-Dist: numpy (>=1.26.4,<2.0.0)
Requires-Dist: pytest (>=8.1.1,<9.0.0)
Project-URL: Bug Tracker, https://github.com/delanoflipse/pytest-energy-reporter/issues
Project-URL: Documentation, https://github.com/delanoflipse/pytest-energy-reporter
Project-URL: Homepage, https://github.com/delanoflipse/pytest-energy-reporter
Project-URL: Repository, https://github.com/delanoflipse/pytest-energy-reporter
